kollet/__init__.py
kollet/errors.py
kollet/kollet.py
tests/__init__.py
tests/main.py
kollet_io-0.1.0.dist-info/LICENSE
kollet_io-0.1.0.dist-info/METADATA
kollet_io-0.1.0.dist-info/WHEEL
kollet_io-0.1.0.dist-info/top_level.txt
kollet_io-0.1.0.dist-info/RECORD
