Metadata-Version: 2.1
Name: kollet-io
Version: 0.1.0
Summary: Python API wrapper for the Kollet Merchant API
Home-page: https://github.com/kollet-io/kollet-python-api-wrapper.git
Author: Kollet.io
Author-email: support@kollet.io
License: MIT
Keywords: Kollet,Kollet API,Merchant API Wrapper,Kollet API Wrapper,Kollet Merchant API
Platform: UNKNOWN
Classifier: Programming Language :: Python :: 3
Classifier: License :: OSI Approved :: MIT License
Classifier: Operating System :: OS Independent
Requires-Python: >=3.6
License-File: LICENSE
Requires-Dist: requests
